brewtils/__init__.py
brewtils/__version__.py
brewtils/auto_decorator.py
brewtils/choices.py
brewtils/config.py
brewtils/decorators.py
brewtils/display.py
brewtils/errors.py
brewtils/log.py
brewtils/models.py
brewtils/pika.py
brewtils/plugin.py
brewtils/queues.py
brewtils/request_handling.py
brewtils/schema_parser.py
brewtils/schemas.py
brewtils/specification.py
brewtils/stoppable_thread.py
brewtils/resolvers/__init__.py
brewtils/resolvers/bytes.py
brewtils/resolvers/chunks.py
brewtils/resolvers/identity.py
brewtils/resolvers/manager.py
brewtils/rest/__init__.py
brewtils/rest/client.py
brewtils/rest/easy_client.py
brewtils/rest/publish_client.py
brewtils/rest/system_client.py
brewtils/test/__init__.py
brewtils/test/comparable.py
brewtils/test/fixtures.py
brewtils-3.31.1.dist-info/licenses/AUTHORS.rst
brewtils-3.31.1.dist-info/licenses/LICENSE.md
brewtils-3.31.1.dist-info/METADATA
brewtils-3.31.1.dist-info/WHEEL
brewtils-3.31.1.dist-info/top_level.txt
brewtils-3.31.1.dist-info/RECORD
