Metadata-Version: 2.4
Name: brewtils
Version: 3.31.1
Summary: Beer-garden plugin and utility library
Home-page: https://beer-garden.io/
Author: The Beer-garden Team
Author-email:  
License: MIT
Classifier: Intended Audience :: Developers
Classifier: License :: OSI Approved :: MIT License
Classifier: Programming Language :: Python :: 3 :: Only
Classifier: Programming Language :: Python :: 3.11
Classifier: Programming Language :: Python :: 3.12
Classifier: Programming Language :: Python :: 3.13
Classifier: Topic :: Software Development :: Libraries :: Python Modules
License-File: LICENSE.md
License-File: AUTHORS.rst
Requires-Dist: appdirs<2
Requires-Dist: lark-parser<1
Requires-Dist: marshmallow<4.1,>=4.0
Requires-Dist: packaging
Requires-Dist: pika<=1.4,>=1.0.1
Requires-Dist: requests<3
Requires-Dist: simplejson<4
Requires-Dist: wrapt
Requires-Dist: yapconf<0.5,>=0.3.7
Dynamic: author
Dynamic: author-email
Dynamic: classifier
Dynamic: description
Dynamic: description-content-type
Dynamic: home-page
Dynamic: license
Dynamic: license-file
Dynamic: requires-dist
Dynamic: summary
